cortexa/__init__.py
cortexa/core.py
cortexa/llm.py
cortexa/memory.py
cortexa/prompts.py
cortexa-1.0.1.dist-info/licenses/LICENSE
cortexa-1.0.1.dist-info/METADATA
cortexa-1.0.1.dist-info/WHEEL
cortexa-1.0.1.dist-info/top_level.txt
cortexa-1.0.1.dist-info/RECORD
