Metadata-Version: 2.4
Name: cortexa
Version: 1.0.1
Summary: A basic AI model embedded in python
Author: Samarth Chugh
License: MIT
Requires-Python: >=3.6
License-File: LICENSE
Dynamic: license-file
